<?xml version='1.0' encoding='ISO-8859-1' ?>

<?xml-stylesheet href='../style/IndexTermsPage.xsl' type='text/xsl'?>
<!--
  XML-Page generated by PENELOPE.
  1999 Araneus Group and University 'Roma Tre', Rome, ITALY
-->
<!DOCTYPE IndexTermsPage SYSTEM '../DTD/IndexTermsPage.dtd'>

<IndexTermsPage>

 <title ArticleCode="987042">A DBMS for Large Design Automation Databases.</title>
 <authors>
 <author AuthorPosition="00">Mark N. Haynie</author>
 </authors>
 <confName>ACM SIGMOD Conference</confName>
 <confYear>1988</confYear>
 <volume>17</volume>
 <number>3</number>
 <initPage>269</initPage>
 <endPage>276</endPage>
 <fullText >
 	<size></size>
 </fullText>
 <abstract>Large capacity Design Automation (CAD/CAM) database management systems require special capabilities over and above what commercial DBMSs or small workstation-based CAD/CAM systems provide. This paper describes one such system, Tacoma, used at Amdahl Corpo</abstract>
 <generalTerms></generalTerms>
 <categoryAndSubjectDescriptors></categoryAndSubjectDescriptors>
</IndexTermsPage>

